Theory/theo06/Mult/Verilog/xMult.v
`timescale 1ns / 1ps

module xMult
#(  parameter bus_width = 16)
(
        input  [bus_width-1:0] A,
        input  [bus_width-1:0] B,
        output reg [bus_width*2-1:0]     C
		);

 always @ *
    C = A * B;
endmodule

Theory/theo06/Mult/Verilog/xMult_tb.v
`timescale 1ns / 1ps


module xtop_tb;

   //parameters
   parameter clk_period = 10;

   //
   // Interface signals
   //
   reg clk;
   reg rst;
   wire trap;


   //exteranl parallel interface
   wire               par_we;
   reg [15:0]  A;
   reg [15:0] B;
   wire [31:0] C;

   //iterator and timer
   integer 		   i, start_time;



   reg [31:0] data_out_ref;
   wire [31:0] data_out;
   wire       data_out_valid;


   // Instantiate the Unit Under Test (UUT)
   xMult  #(.bus_width(16)) nultiplier (
         .A(A),
         .B(B),
         .C(C)
	     );

   initial begin

   $dumpfile("top.vcd");
   $dumpvars();

      #50.1 A=16'h0002;
      B=16'h0000;

      for(i=0; i < 10; i++) begin
      data_out_ref = (i+2)*2;
      #10 B = i+2;

      end

      $finish;
   end // initial begin
   // CLOCK
   always
     #(clk_period/2) clk = ~clk;

   // show registers


endmodule

Theory/theo06/Mult/Verilog/top.vcd
$date
	Tue Oct  8 22:41:54 2019
$end
$version
	Icarus Verilog
$end
$timescale
	1ps
$end
$scope module xtop_tb $end
$var wire 32 ! C [31:0] $end
$var reg 16 " A [15:0] $end
$var reg 16 # B [15:0] $end
$var reg 1 $ clk $end
$var reg 32 % data_out_ref [31:0] $end
$var integer 32 & i [31:0] $end
$scope module nultiplier $end
$var wire 16 ' A [15:0] $end
$var wire 16 ( B [15:0] $end
$var reg 32 ) C [31:0] $end
$upscope $end
$upscope $end
$enddefinitions $end
#0
$dumpvars
bx )
bx (
bx '
bx &
bx %
x$
bx #
bx "
bx !
$end
#50100
b0 !
b0 )
b100 %
b0 &
b0 #
b0 (
b10 "
b10 '
#60100
b100 !
b100 )
b110 %
b1 &
b10 #
b10 (
#70100
b110 !
b110 )
b1000 %
b10 &
b11 #
b11 (
#80100
b1000 !
b1000 )
b1010 %
b11 &
b100 #
b100 (
#90100
b1010 !
b1010 )
b1100 %
b100 &
b101 #
b101 (
#100100
b1100 !
b1100 )
b1110 %
b101 &
b110 #
b110 (
#110100
b1110 !
b1110 )
b10000 %
b110 &
b111 #
b111 (
#120100
b10000 !
b10000 )
b10010 %
b111 &
b1000 #
b1000 (
#130100
b10010 !
b10010 )
b10100 %
b1000 &
b1001 #
b1001 (
#140100
b10100 !
b10100 )
b10110 %
b1001 &
b1010 #
b1010 (
#150100
b10110 !
b10110 )
b1010 &
b1011 #
b1011 (
